APS4-Q4/control_unit.v
module control_unit 
    (output reg IR_Load, 
     output reg MAR_Load, 
     output reg PC_Load, PC_Inc, 
     output reg A_Load, B_Load,
     output reg CCR_Load,
     output reg [2:0] ALU_Sel,
     output reg [1:0] Bus1_Sel, Bus2_Sel,
     output reg write, 
     input wire [7:0] IR, 
     input wire [3:0] CCR_Result,
     input wire Clk, Reset);
                 
    reg [7:0] current_state, next_state;

    // --- Definições de Estados ---
    parameter S0_FETCH = 8'h00, S1_FETCH = 8'h01, S2_FETCH = 8'h02,
              S3_DECODE = 8'h03,
              S4_LDA_IMM = 8'h04, S5_LDA_IMM = 8'h05, S6_LDA_IMM = 8'h06,
              S4_LDA_DIR = 8'h07, S5_LDA_DIR = 8'h08, S6_LDA_DIR = 8'h09,
              S7_LDA_DIR = 8'h0A, S8_LDA_DIR = 8'h0B,
              // NOVOS ESTADOS INSERIDOS
              S4_ADD_IMM = 8'h0C, S5_ADD_IMM = 8'h0D, S6_ADD_IMM = 8'h0E,
              S4_STA_DIR = 8'h0F, S5_STA_DIR = 8'h10, S6_STA_DIR = 8'h11,
              S7_STA_DIR = 8'h12,
              S4_BRZ_DIR = 8'h13, S5_BRZ_DIR = 8'h14, S6_BRZ_DIR = 8'h15;

    // --- Definições de Opcodes ---
    parameter [7:0] LDA_IMM = 8'h01; 
    parameter [7:0] LDA_DIR = 8'h02; 
    parameter [7:0] ADD_IMM = 8'h11; 
    parameter [7:0] STA_DIR = 8'h03; 
    parameter [7:0] BRZ_DIR = 8'h30; 
               
    // --- Inicialização ---
    initial begin
        current_state = S0_FETCH;
        next_state = S0_FETCH;
        // Reinicializando todos os sinais corretamente
        {IR_Load, MAR_Load, PC_Load, PC_Inc, A_Load, B_Load, CCR_Load, write} = 8'b0;
        ALU_Sel = 3'b000;
        Bus1_Sel = 2'b00;
        Bus2_Sel = 2'b00; // Valor de reset mais seguro
    end
  

    // --- 1. STATE_MEMORY (Lógica Sequencial) ---
    always @ (posedge Clk or negedge Reset)
        begin: STATE_MEMORY
            if (!Reset)
                current_state <= S0_FETCH;
            else
                current_state <= next_state;
        end
    
    // --- 2. NEXT_STATE_LOGIC (Lógica do Próximo Estado) ---
    always @ (current_state, IR, CCR_Result)
        begin: NEXT_STATE_LOGIC
            next_state = S0_FETCH; 
            
            case (current_state)
                S0_FETCH : next_state = S1_FETCH;
                S1_FETCH : next_state = S2_FETCH;
                S2_FETCH : next_state = S3_DECODE;
                
                S3_DECODE : begin
                    case (IR)
                        LDA_IMM : next_state = S4_LDA_IMM;
                        LDA_DIR : next_state = S4_LDA_DIR;
                        ADD_IMM : next_state = S4_ADD_IMM; // Adicionado
                        STA_DIR : next_state = S4_STA_DIR; // Adicionado
                        BRZ_DIR : next_state = S4_BRZ_DIR; // Adicionado
                        default: next_state = S0_FETCH;
                    endcase
                end
            
                // --- EXECUTE: LDA_IMM ---
                S4_LDA_IMM : next_state = S5_LDA_IMM; 
                S5_LDA_IMM : next_state = S6_LDA_IMM; 
                S6_LDA_IMM : next_state = S0_FETCH;
                
                // --- EXECUTE: ADD_IMM ---
                S4_ADD_IMM : next_state = S5_ADD_IMM; 
                S5_ADD_IMM : next_state = S6_ADD_IMM;
                S6_ADD_IMM : next_state = S0_FETCH; 

                // --- EXECUTE: LDA_DIR ---
                S4_LDA_DIR : next_state = S5_LDA_DIR;
                S5_LDA_DIR : next_state = S6_LDA_DIR;
                S6_LDA_DIR : next_state = S7_LDA_DIR;
                S7_LDA_DIR : next_state = S8_LDA_DIR;
                S8_LDA_DIR : next_state = S0_FETCH;
                
                // --- EXECUTE: STA_DIR ---
                S4_STA_DIR : next_state = S5_STA_DIR;
                S5_STA_DIR : next_state = S6_STA_DIR;
                S6_STA_DIR : next_state = S7_STA_DIR;
                S7_STA_DIR : next_state = S0_FETCH;
                
                // --- EXECUTE: BRZ_DIR ---
                S4_BRZ_DIR : next_state = S5_BRZ_DIR;
                S5_BRZ_DIR : begin 
                    if (CCR_Result[2]) // Se Zero Flag (Z) é 1
                        next_state = S6_BRZ_DIR; 
                    else
                        next_state = S0_FETCH;  
                end
                S6_BRZ_DIR : next_state = S0_FETCH; 

                default : next_state = S0_FETCH;
            endcase
        end
    
    // --- 3. OUTPUT_LOGIC (Lógica de Saída) ---
    always @ (current_state)
        begin: OUTPUT_LOGIC
            // Reset de Sinais no início de cada estado
            {IR_Load, MAR_Load, PC_Load, PC_Inc, A_Load, B_Load, CCR_Load, write} = 8'b0;
            ALU_Sel = 3'b000; // Padrão ADD
            Bus1_Sel = 2'b00; // Padrão PC
            Bus2_Sel = 2'b00; // Padrão ALU
            
            case (current_state)
                // --- Ciclo FETCH (S0, S1, S2) ---
                S0_FETCH : begin // PC -> MAR
                    MAR_Load = 1;
                    Bus1_Sel = 2'b00; // PC -> Bus1
                    Bus2_Sel = 2'b01; // Bus1 -> MAR
                end
                S1_FETCH : begin // Mem -> IR, PC++
                    IR_Load = 1;
                    PC_Inc = 1;
                    ALU_Sel = 3'b001; // PC + 1
                    Bus2_Sel = 2'b10; // Memória -> IR
                end
                S2_FETCH : begin // PC -> MAR (Endereço do Operando)
                    MAR_Load = 1;
                    Bus1_Sel = 2'b00; // PC -> Bus1
                    Bus2_Sel = 2'b01; // Bus1 -> MAR
                end
                S3_DECODE : ; // Nenhum sinal ativo
                
                // --- EXECUTE: LDA_IMM ---
                S4_LDA_IMM : begin // B <- Memoria, PC++
                    B_Load = 1;      // Carrega dado imediato lido
                    PC_Inc = 1;
                    ALU_Sel = 3'b001; // PC + 1
                    Bus2_Sel = 2'b10; // Memória -> B
                end
                S5_LDA_IMM : begin // A <- B, CCR_Load
                    A_Load = 1;
                    CCR_Load = 1;
                    Bus1_Sel = 2'b10; // B -> Bus1
                    Bus2_Sel = 2'b01; // Bus1 -> A
                end
                S6_LDA_IMM : ; 

                // --- EXECUTE: ADD_IMM ---
                S4_ADD_IMM : begin // B <- Memoria, PC++
                    B_Load = 1;      // Carrega dado imediato lido
                    PC_Inc = 1;
                    ALU_Sel = 3'b001; // PC + 1
                    Bus2_Sel = 2'b10; // Memória -> B
                end
                S5_ADD_IMM : begin // A <- A + B, CCR_Load
                    A_Load = 1;
                    CCR_Load = 1;
                    Bus1_Sel = 2'b01; // A -> Bus1 (para ALU)
                    Bus2_Sel = 2'b00; // ALU -> A
                    ALU_Sel = 3'b000; // A + B
                end
                S6_ADD_IMM : ;
                
                // --- EXECUTE: STA_DIR ---
                S7_STA_DIR : begin // Escrita A -> Memória
                    write = 1;
                    Bus1_Sel = 2'b01; // A (Dado) -> Barramento
                end
                
                // --- EXECUTE: BRZ_DIR ---
                S4_BRZ_DIR : begin // MAR <- PC (Endereço Alto), PC++
                    MAR_Load = 1;
                    PC_Inc = 1;
                    ALU_Sel = 3'b001;
                    Bus2_Sel = 2'b10; // Memória -> MAR
                end
                S5_BRZ_DIR : begin // MAR <- PC (Endereço Baixo)
                    MAR_Load = 1; 
                    Bus1_Sel = 2'b00; 
                    Bus2_Sel = 2'b01; 
                end
                S6_BRZ_DIR : begin // PC <- Endereço de Desvio (Apenas se desvio tomado)
                    PC_Load = 1;
                    Bus2_Sel = 2'b10; // Memória (Dado de Endereço) -> PC
                end
                
                default: ;
            endcase
        end
endmodule

APS4/APS4/control_unit_tb.v
`timescale 1ns / 1ps
`include "control_unit.v"

module control_unit_tb;

    // --- Sinais internos para o Testbench ---
    reg Clk;
    reg Reset;
    // IR_tb será usado para simular tanto o Opcode quanto o Dado/Endereço
    reg [7:0] IR_tb;         
    reg [3:0] CCR_Result_tb; 

    // --- Sinais de Saída da Unidade de Controle (DUT) ---
    wire IR_Load, MAR_Load;
    wire PC_Load, PC_Inc;
    wire A_Load, B_Load;
    wire CCR_Load;
    wire [2:0] ALU_Sel;
    wire [1:0] Bus1_Sel, Bus2_Sel;
    wire write;

    // --- Parâmetros de Opcodes ---
    parameter [7:0] BRZ_DIR = 8'h30; 
    
    // --- Instanciação da Unidade de Controle (DUT) ---
    control_unit DUT (
        .IR_Load(IR_Load),
        .MAR_Load(MAR_Load),
        .PC_Load(PC_Load),
        .PC_Inc(PC_Inc),
        .A_Load(A_Load),
        .B_Load(B_Load),
        .CCR_Load(CCR_Load),
        .ALU_Sel(ALU_Sel),
        .Bus1_Sel(Bus1_Sel),
        .Bus2_Sel(Bus2_Sel),
        .write(write),
        .IR(IR_tb),
        .CCR_Result(CCR_Result_tb),
        .Clk(Clk),
        .Reset(Reset)
    );

    // --- Memória Simulada ---
    reg [7:0] instruction_stream [0:255]; 
    reg [7:0] PC_sim;
    
    // --- Gerador de Clock ---
    parameter CLK_PERIOD = 10;
    initial begin
        Clk = 0;
        forever #(CLK_PERIOD / 2) Clk = ~Clk;
    end

    // --- Lógica de Simulação Principal (Setup) ---
    initial begin
        // --- Programa de Teste na Memória Simulada ---
        instruction_stream[8'h00] = 8'h01; // LDA_IMM
        instruction_stream[8'h01] = 8'hAA; 
        instruction_stream[8'h02] = 8'h11; // ADD_IMM
        instruction_stream[8'h03] = 8'h05;
        instruction_stream[8'h04] = 8'h03; // STA_DIR
        instruction_stream[8'h05] = 8'h01; 
        instruction_stream[8'h06] = 8'h50; 
        instruction_stream[8'h07] = 8'h30; // BRZ_DIR
        instruction_stream[8'h08] = 8'h00; // Endereço Alto (ignoramos)
        instruction_stream[8'h09] = 8'h80; // Endereço Baixo/Destino do Salto
        instruction_stream[8'h80] = 8'hFF; // END (Novo Destino)

        $dumpfile("control_unit_tb.vcd");
        $dumpvars(0, control_unit_tb);
        
        // Reset
        Reset = 0;
        IR_tb = 8'hFF;
        CCR_Result_tb = 4'b0000;
        PC_sim = 8'h00; 

        #10 Reset = 1; 
        #20; 
        
        $display("--- Start Simulation ---");
        
        repeat (50) @(posedge Clk);
        
        $display("--- End Simulation ---");
        $finish;
    end
    
    // --- Lógica Corrigida para simular a busca de instrução/operando ---
    always @(posedge Clk) begin
        
        // --- Leitura do Dado/Instrução da Memória para o Barramento/IR_tb ---
        // Bus2_Sel == 2'b10 (0x2) significa que a memória está colocando um dado no barramento
        // (Este dado precisa ser capturado pelo IR_tb para ser usado pelo PC_Load ou B_Load)
        if (Bus2_Sel == 2'b10) begin
             // Se a memória está lendo, o IR_tb recebe o dado no PC atual.
             IR_tb <= instruction_stream[PC_sim];
        end

        // 1. Carga e Incremento do PC (Prioridade PC_Load > PC_Inc)
        if (PC_Load) begin
            // PC_Load ativo (S6_BRZ_DIR): PC carrega o valor lido da memória (que está no IR_tb)
            PC_sim <= IR_tb; 
        end else if (PC_Inc) begin
            PC_sim <= PC_sim + 1;
        end
        
        // 2. Configurar CCR para teste de BRZ (PC=08, IR=30)
        // Forçamos Z=1 no momento em que o opcode BRZ (30) está no IR_tb e PC=08
        if (PC_sim == 8'h08 && IR_tb == BRZ_DIR) begin
             CCR_Result_tb <= 4'b0100; // Z=1 (Desvio Tomado)
        end else begin
             CCR_Result_tb <= 4'b0000;
        end
        
        $display("Time: %0d | PC: %h | IR: %h | IR_Load: %b | B_Load: %b | PC_Load: %b | PC_Inc: %b | write: %b | CCR_Z: %b",
            $time, PC_sim, IR_tb, IR_Load, B_Load, PC_Load, PC_Inc, write, CCR_Result_tb[2]);
    end

endmodule

APS4/APS4/control_unit_tb.vcd
$date
	Fri Dec 12 14:02:50 2025
$end
$version
	Icarus Verilog
$end
$timescale
	1ps
$end
$scope module control_unit_tb $end
$var wire 1 ! write $end
$var wire 1 " PC_Load $end
$var wire 1 # PC_Inc $end
$var wire 1 $ MAR_Load $end
$var wire 1 % IR_Load $end
$var wire 1 & CCR_Load $end
$var wire 2 ' Bus2_Sel [1:0] $end
$var wire 2 ( Bus1_Sel [1:0] $end
$var wire 1 ) B_Load $end
$var wire 1 * A_Load $end
$var wire 3 + ALU_Sel [2:0] $end
$var parameter 8 , BRZ_DIR $end
$var parameter 32 - CLK_PERIOD $end
$var reg 4 . CCR_Result_tb [3:0] $end
$var reg 1 / Clk $end
$var reg 8 0 IR_tb [7:0] $end
$var reg 8 1 PC_sim [7:0] $end
$var reg 1 2 Reset $end
$scope module DUT $end
$var wire 4 3 CCR_Result [3:0] $end
$var wire 1 / Clk $end
$var wire 8 4 IR [7:0] $end
$var wire 1 2 Reset $end
$var parameter 8 5 ADD_IMM $end
$var parameter 8 6 BRZ_DIR $end
$var parameter 8 7 LDA_DIR $end
$var parameter 8 8 LDA_IMM $end
$var parameter 8 9 S0_FETCH $end
$var parameter 8 : S1_FETCH $end
$var parameter 8 ; S2_FETCH $end
$var parameter 8 < S3_DECODE $end
$var parameter 8 = S4_ADD_IMM $end
$var parameter 8 > S4_BRZ_DIR $end
$var parameter 8 ? S4_LDA_DIR $end
$var parameter 8 @ S4_LDA_IMM $end
$var parameter 8 A S4_STA_DIR $end
$var parameter 8 B S5_ADD_IMM $end
$var parameter 8 C S5_BRZ_DIR $end
$var parameter 8 D S5_LDA_DIR $end
$var parameter 8 E S5_LDA_IMM $end
$var parameter 8 F S5_STA_DIR $end
$var parameter 8 G S6_ADD_IMM $end
$var parameter 8 H S6_BRZ_DIR $end
$var parameter 8 I S6_LDA_DIR $end
$var parameter 8 J S6_LDA_IMM $end
$var parameter 8 K S6_STA_DIR $end
$var parameter 8 L S7_LDA_DIR $end
$var parameter 8 M S7_STA_DIR $end
$var parameter 8 N S8_LDA_DIR $end
$var parameter 8 O STA_DIR $end
$var reg 3 P ALU_Sel [2:0] $end
$var reg 1 * A_Load $end
$var reg 1 ) B_Load $end
$var reg 2 Q Bus1_Sel [1:0] $end
$var reg 2 R Bus2_Sel [1:0] $end
$var reg 1 & CCR_Load $end
$var reg 1 % IR_Load $end
$var reg 1 $ MAR_Load $end
$var reg 1 # PC_Inc $end
$var reg 1 " PC_Load $end
$var reg 8 S current_state [7:0] $end
$var reg 8 T next_state [7:0] $end
$var reg 1 ! write $end
$scope begin NEXT_STATE_LOGIC $end
$upscope $end
$scope begin OUTPUT_LOGIC $end
$upscope $end
$scope begin STATE_MEMORY $end
$upscope $end
$upscope $end
$upscope $end
$enddefinitions $end
$comment Show the parameter values. $end
$dumpall
b11 O
b1011 N
b10010 M
b1010 L
b10001 K
b110 J
b1001 I
b10101 H
b1110 G
b10000 F
b101 E
b1000 D
b10100 C
b1101 B
b1111 A
b100 @
b111 ?
b10011 >
b1100 =
b11 <
b10 ;
b1 :
b0 9
b1 8
b10 7
b110000 6
b10001 5
b1010 -
b110000 ,
$end
#0
$dumpvars
b1 T
b0 S
b1 R
b0 Q
b0 P
b11111111 4
b0 3
02
b0 1
b11111111 0
0/
b0 .
b0 +
0*
0)
b0 (
b1 '
0&
0%
1$
0#
0"
0!
$end
#5000
1/
#10000
0/
12
#15000
b1 +
b1 P
1#
1%
b10 '
b10 R
0$
b10 T
b1 S
1/
#20000
0/
#25000
1$
b1 '
b1 R
b0 +
b0 P
0%
0#
b11 T
b10 S
b1 1
b1 0
b1 4
1/
#30000
0/
#35000
b0 '
b0 R
0$
b100 T
b11 S
1/
#40000
0/
#45000
b10 '
b10 R
b1 +
b1 P
1#
1)
b101 T
b100 S
1/
#50000
0/
#55000
b10 (
b10 Q
1&
1*
b1 '
b1 R
b0 +
b0 P
0#
0)
b110 T
b101 S
b10 1
b10101010 0
b10101010 4
1/
#60000
0/
#65000
b0 '
b0 R
b0 (
b0 Q
0*
0&
b0 T
b110 S
1/
#70000
0/
#75000
b1 '
b1 R
1$
b1 T
b0 S
1/
#80000
0/
#85000
b1 +
b1 P
1#
1%
b10 '
b10 R
0$
b10 T
b1 S
1/
#90000
0/
#95000
1$
b1 '
b1 R
b0 +
b0 P
0%
0#
b11 T
b10 S
b11 1
b10001 0
b10001 4
1/
#100000
0/
#105000
b0 '
b0 R
0$
b1100 T
b11 S
1/
#110000
0/
#115000
b10 '
b10 R
b1 +
b1 P
1#
1)
b1101 T
b1100 S
1/
#120000
0/
#125000
b1 (
b1 Q
1&
1*
b0 '
b0 R
b0 +
b0 P
0#
0)
b1110 T
b1101 S
b100 1
b101 0
b101 4
1/
#130000
0/
#135000
b0 (
b0 Q
0*
0&
b0 T
b1110 S
1/
#140000
0/
#145000
b1 '
b1 R
1$
b1 T
b0 S
1/
#150000
0/
#155000
b1 +
b1 P
1#
1%
b10 '
b10 R
0$
b10 T
b1 S
1/
#160000
0/
#165000
1$
b1 '
b1 R
b0 +
b0 P
0%
0#
b11 T
b10 S
b101 1
b11 0
b11 4
1/
#170000
0/
#175000
b0 '
b0 R
0$
b1111 T
b11 S
1/
#180000
0/
#185000
b10000 T
b1111 S
1/
#190000
0/
#195000
b10001 T
b10000 S
1/
#200000
0/
#205000
b10010 T
b10001 S
1/
#210000
0/
#215000
b1 (
b1 Q
1!
b0 T
b10010 S
1/
#220000
0/
#225000
b1 '
b1 R
1$
b0 (
b0 Q
0!
b1 T
b0 S
1/
#230000
0/
#235000
b1 +
b1 P
1#
1%
b10 '
b10 R
0$
b10 T
b1 S
1/
#240000
0/
#245000
1$
b1 '
b1 R
b0 +
b0 P
0%
0#
b11 T
b10 S
b110 1
b1 0
b1 4
1/
#250000
0/
#255000
b0 '
b0 R
0$
b100 T
b11 S
1/
#260000
0/
#265000
b10 '
b10 R
b1 +
b1 P
1#
1)
b101 T
b100 S
1/
#270000
0/
#275000
b10 (
b10 Q
1&
1*
b1 '
b1 R
b0 +
b0 P
0#
0)
b110 T
b101 S
b111 1
b1010000 0
b1010000 4
1/
#280000
0/
#285000
b0 '
b0 R
b0 (
b0 Q
0*
0&
b0 T
b110 S
1/
#290000
0/
#295000
b1 '
b1 R
1$
b1 T
b0 S
1/
#300000
0/
#305000
b1 +
b1 P
1#
1%
b10 '
b10 R
0$
b10 T
b1 S
1/
#310000
0/
#315000
1$
b1 '
b1 R
b0 +
b0 P
0%
0#
b11 T
b10 S
b1000 1
b110000 0
b110000 4
1/
#320000
0/
#325000
b0 '
b0 R
0$
b10011 T
b11 S
b100 .
b100 3
1/
#330000
0/
#335000
b10 '
b10 R
b1 +
b1 P
1#
1$
b10100 T
b10011 S
1/
#340000
0/
#345000
b1 '
b1 R
b0 +
b0 P
1$
0#
b10101 T
b10100 S
b1001 1
b0 0
b0 4
1/
#350000
0/
#355000
1"
b10 '
b10 R
0$
b0 T
b10101 S
b0 .
b0 3
1/
#360000
0/
#365000
1$
b1 '
b1 R
0"
b1 T
b0 S
b0 1
b10000000 0
b10000000 4
1/
#370000
0/
#375000
b1 +
b1 P
1#
1%
b10 '
b10 R
0$
b10 T
b1 S
1/
#380000
0/
#385000
1$
b1 '
b1 R
b0 +
b0 P
0%
0#
b11 T
b10 S
b1 1
b1 0
b1 4
1/
#390000
0/
#395000
b0 '
b0 R
0$
b100 T
b11 S
1/
#400000
0/
#405000
b10 '
b10 R
b1 +
b1 P
1#
1)
b101 T
b100 S
1/
#410000
0/
#415000
b10 (
b10 Q
1&
1*
b1 '
b1 R
b0 +
b0 P
0#
0)
b110 T
b101 S
b10 1
b10101010 0
b10101010 4
1/
#420000
0/
#425000
b0 '
b0 R
b0 (
b0 Q
0*
0&
b0 T
b110 S
1/
#430000
0/
#435000
b1 '
b1 R
1$
b1 T
b0 S
1/
#440000
0/
#445000
b1 +
b1 P
1#
1%
b10 '
b10 R
0$
b10 T
b1 S
1/
#450000
0/
#455000
1$
b1 '
b1 R
b0 +
b0 P
0%
0#
b11 T
b10 S
b11 1
b10001 0
b10001 4
1/
#460000
0/
#465000
b0 '
b0 R
0$
b1100 T
b11 S
1/
#470000
0/
#475000
b10 '
b10 R
b1 +
b1 P
1#
1)
b1101 T
b1100 S
1/
#480000
0/
#485000
b1 (
b1 Q
1&
1*
b0 '
b0 R
b0 +
b0 P
0#
0)
b1110 T
b1101 S
b100 1
b101 0
b101 4
1/
#490000
0/
#495000
b0 (
b0 Q
0*
0&
b0 T
b1110 S
1/
#500000
0/
#505000
b1 '
b1 R
1$
b1 T
b0 S
1/
#510000
0/
#515000
b1 +
b1 P
1#
1%
b10 '
b10 R
0$
b10 T
b1 S
1/
#520000
0/
#525000
1$
b1 '
b1 R
b0 +
b0 P
0%
0#
b11 T
b10 S
b101 1
b11 0
b11 4
1/
