APS3-Q5/modelo_comportamental.v
`timescale 1ps/1ps

module modelo_comportamental (
    input  wire clk,
    input  wire res,
    input  wire CAR,
    input  wire TIMEOUT,
    output reg VERDE,
    output reg AMARELO,
    output reg VERMELHO
);

    parameter S_VERDE    = 2'b00;
    parameter S_AMARELO  = 2'b01;
    parameter S_VERMELHO = 2'b10;

    reg [1:0] state, next_state;

    // Atualiza o estado na borda do clock
    always @(posedge clk or negedge res) begin
        if (!res)
            state <= S_VERDE;
        else
            state <= next_state;
    end

    // Define a lógica de transição de estados
    always @(*) begin
        case(state)
            S_VERDE:    next_state = (CAR) ? S_AMARELO : S_VERDE;
            S_AMARELO:  next_state = S_VERMELHO;
            S_VERMELHO: next_state = (TIMEOUT) ? S_VERDE : S_VERMELHO;
            default:    next_state = S_VERDE;
        endcase
    end

    // Atualiza as saídas sincronizadas com o estado
    always @(posedge clk or negedge res) begin
        if(!res) begin
            VERDE    <= 1;
            AMARELO  <= 0;
            VERMELHO <= 0;
        end else begin
            case(next_state)
                S_VERDE: begin VERDE <= 1; AMARELO <= 0; VERMELHO <= 0; end
                S_AMARELO: begin VERDE <= 0; AMARELO <= 1; VERMELHO <= 0; end
                S_VERMELHO: begin VERDE <= 0; AMARELO <= 0; VERMELHO <= 1; end
            endcase
        end
    end
endmodule

APS2-Q3/lib.v
`timescale 1ps/1ps

module NOT (output wire F, input wire A);
    nand(F,A,A);
    
endmodule

module AND (output wire F, input wire A, B);
    wire Fn;

    nand(Fn, A, B);
    nand(F, Fn, Fn);

endmodule

module OR (output wire F, input wire A, B);
    wire f1, f2;

    nand(f1, A, A);
    nand(f2, B, B);
    nand(F, f1, f2);

endmodule

module XOR (output wire F, input wire A, B);
    wire An, Bn, f1, f2;

    nand(An, A, A);
    nand(Bn, B, B);

    nand(f1, An, B);
    nand(f2, A, Bn);

    nand(F, f1, f2);

endmodule

module not8b
	(output wire [7:0] F,
	input wire [7:0] A);

	NOT not1 (F[0], A[0]);
    NOT not2 (F[1], A[1]);
    NOT not3 (F[2], A[2]);
    NOT not4 (F[3], A[3]);
    NOT not5 (F[4], A[4]);
    NOT not6 (F[5], A[5]);
    NOT not7 (F[6], A[6]);
    NOT not8 (F[7], A[7]);
	
endmodule

module or8bitwb
	(output wire F,
	input wire [7:0] A);

	wire F1, F2, F3, F4, F5, F6;

    OR or1 (F1, A[0], A[1]);
    OR or2 (F2, A[2], A[3]);
    OR or3 (F3, A[4], A[5]);
    OR or4 (F4, A[6], A[7]);

    OR or5 (F5, F1, F2);
    OR or6 (F6, F3, F4);

    OR or7 (F, F5, F6);
	
endmodule

module and8b
	(output wire [7:0] F,
	input wire [7:0] A,B);

    AND and1 (F[0], A[0], B[0]);
    AND and2 (F[1], A[1], B[1]);
    AND and3 (F[2], A[2], B[2]);
    AND and4 (F[3], A[3], B[3]);
    AND and5 (F[4], A[4], B[4]);
    AND and6 (F[5], A[5], B[5]);
    AND and7 (F[6], A[6], B[6]);
    AND and8 (F[7], A[7], B[7]);
	
endmodule

module or8b
	(output wire [7:0] F,
	input wire [7:0] A, B);

	OR or1 (F[0], A[0], B[0]);
    OR or2 (F[1], A[1], B[1]);
    OR or3 (F[2], A[2], B[2]);
    OR or4 (F[3], A[3], B[3]);
    OR or5 (F[4], A[4], B[4]);
    OR or6 (F[5], A[5], B[5]);
    OR or7 (F[6], A[6], B[6]);
    OR or8 (F[7], A[7], B[7]);

endmodule

module xor8b (
    output wire [7:0] F,
    input wire [7:0] A, B
);

    XOR xor1 (F[0], A[0], B[0]);
    XOR xor2 (F[1], A[1], B[1]);
    XOR xor3 (F[2], A[2], B[2]);
    XOR xor4 (F[3], A[3], B[3]);
    XOR xor5 (F[4], A[4], B[4]);
    XOR xor6 (F[5], A[5], B[5]);
    XOR xor7 (F[6], A[6], B[6]);
    XOR xor8 (F[7], A[7], B[7]);

endmodule

module mux8b(
    output wire [7:0] F,
    input wire [7:0] A, B,
    input wire Sel
);

    mux_4t1a mux1(F[0], A[0], B[0], 1'b0, 1'b0, {1'b0, Sel});
    mux_4t1a mux2(F[1], A[1], B[1], 1'b0, 1'b0, {1'b0, Sel});
    mux_4t1a mux3(F[2], A[2], B[2], 1'b0, 1'b0, {1'b0, Sel});
    mux_4t1a mux4(F[3], A[3], B[3], 1'b0, 1'b0, {1'b0, Sel});
    mux_4t1a mux5(F[4], A[4], B[4], 1'b0, 1'b0, {1'b0, Sel});
    mux_4t1a mux6(F[5], A[5], B[5], 1'b0, 1'b0, {1'b0, Sel});
    mux_4t1a mux7(F[6], A[6], B[6], 1'b0, 1'b0, {1'b0, Sel});
    mux_4t1a mux8(F[7], A[7], B[7], 1'b0, 1'b0, {1'b0, Sel});

endmodule

module mux8_4to1b(
    output wire [7:0] F,
    input wire [7:0] A, B, C, D,
    input wire [1:0] Sel
);

    wire [7:0] F1, F2;

    mux8b mux0(F1, A, B, Sel[0]);
    mux8b mux1(F2, C, D, Sel[0]);

    mux8b mux2(F, F1, F2, Sel[1]);

endmodule

module dmux8b(
    output wire [7:0] F, G,
    input wire [7:0] A,
    input wire Sel
);

    wire [7:0] Sel8, Sel8n;

    assign Sel8 = {Sel, Sel, Sel, Sel, Sel, Sel, Sel, Sel};
    not8b inv(Sel8n, Sel8);

    and8b andF(F, A, Sel8n);
    and8b andG(G, A, Sel8);

endmodule

module dmux8_1to4b(
    output wire [7:0] W, X, Y, Z,
    input wire [7:0] A,
    input wire [1:0] Sel
);

    wire [7:0] F0, F1;

    dmux8b dmux1(F0, F1, A, Sel[1]);
    dmux8b dmux2(W, X, F0, Sel[0]);
    dmux8b dmux3(Y, Z, F1, Sel[0]);

endmodule


module h_adder  
	(output wire S, C,
	input wire A, B);

	XOR xor1 (S, A, B);
    AND and1 (C, A, B);
	
endmodule

module f_adder
	(output wire S, Cout,
	 input wire A, B, Cin);

	wire S1, C1, C2;

    h_adder ha1 (S1, C1, A, B);
    h_adder ha2 (S, C2, S1, Cin);
    OR or1 (Cout, C1, C2);

endmodule

module adder8b
	(output wire [7:0] S, 
	 output wire Cout,
	input wire [7:0] A, B,
    input wire Cin);

    wire [7:0] C;

	f_adder adder1 (S[0], C[0], A[0], B[0], Cin); 
    f_adder adder2 (S[1], C[1], A[1], B[1], C[0]);
    f_adder adder3 (S[2], C[2], A[2], B[2], C[1]);
    f_adder adder4 (S[3], C[3], A[3], B[3], C[2]);
    f_adder adder5 (S[4], C[4], A[4], B[4], C[3]);
    f_adder adder6 (S[5], C[5], A[5], B[5], C[4]);
    f_adder adder7 (S[6], C[6], A[6], B[6], C[5]);
    f_adder adder8 (S[7], Cout, A[7], B[7], C[6]);
	
endmodule

module mux_4t1a 
        (output wire F, 
        input wire A, B, C, D, 
        input wire [1:0] Sel);

    wire I0i, I1i, I2i, I3i, I0, I1, I2, I3, F1, F2;
    wire Sel0n, Sel1n;

    NOT inv1 (Sel0n, Sel[0]);
    NOT inv2 (Sel1n, Sel[1]);

    AND and1 (I0i, A, Sel0n);
    AND and2 (I0, I0i, Sel1n);

    AND and3 (I1i, B, Sel[0]);
    AND and4 (I1, I1i, Sel1n);

    AND and5 (I2i, C, Sel0n);
    AND and6 (I2, I2i, Sel[1]);

    AND and7 (I3i, D, Sel[0]);
    AND and8 (I3, I3i, Sel[1]);

    OR or1 (F1, I0, I1);
    OR or2 (F2, F1, I2);
    OR or3 (F, F2, I3);

endmodule

APS3-Q2/componentes_new.v
`timescale 1ps/1ps

module dlatch (output reg Q,Qn, 
               input wire C,D);
  
  always @ (C or D)
  	begin
  		if (C==1'b1)
  			begin
  				Q <= D;
  				Qn <= ~D;
  	    	end
  	end
  
endmodule

module dflipflop (output reg Q,Qn, 
                  input wire Clock, Reset, Preset, D);
  
  always @ (posedge Clock or negedge Reset or negedge Preset)
  	begin
	  	if (!Reset)
  			begin
  				Q <= 1'b0;
  				Qn <= 1'b1;
  			end
  		else if (!Preset)
  			begin
  				Q <= 1'b1;
  				Qn <= 1'b0;
  			end
  		else
  			begin
  				Q <= D;
  				Qn <= ~D;
  			end
  	end
endmodule

APS3-Q5/semaforo.v
`timescale 1ps/1ps

module semaforo (
    input wire clk,
    input wire res, 
    input wire CAR,
    input wire TIMEOUT,
    output wire VERDE,
    output wire AMARELO,
    output wire VERMELHO
);

    wire Q0, Q1;
    wire D0, D1;
    wire Q0n, Q1n;

    dflipflop ff0(.Q(Q0), .Qn(Q0n), .Clock(clk), .Reset(res), .Preset(1'b1), .D(D0));
    dflipflop ff1(.Q(Q1), .Qn(Q1n), .Clock(clk), .Reset(res), .Preset(1'b1), .D(D1));
    
    wire notQ0, notQ1;
    NOT inv0(notQ0, Q0);
    NOT inv1(notQ1, Q1);
    
    wire notTIMEOUT;
    NOT invTIMEOUT(notTIMEOUT, TIMEOUT);
    
    wire is_verde;
    AND and_verde_state(is_verde, notQ1, notQ0); 
    
    wire is_amarelo;
    AND and_amarelo_state(is_amarelo, notQ1, Q0); 

    wire is_vermelho;   
    AND and_vermelho_state(is_vermelho, Q1, notQ0); 
    
    wire D0_expr;
    AND and_D0(D0_expr, is_verde, CAR);
    assign D0 = D0_expr;
    
    wire D1_term1;
    wire D1_term2;
    wire D1_expr;
    
    assign D1_term1 = is_amarelo; 
    
    AND and_D1_term2(D1_term2, is_vermelho, notTIMEOUT);
    
    OR or_D1(D1_expr, D1_term1, D1_term2);
    assign D1 = D1_expr;

    assign VERDE = is_verde;
    assign AMARELO = is_amarelo;
    assign VERMELHO = is_vermelho;

endmodule

APS3-Q5/comparar.v
`timescale 1ns/1ps
`include "modelo_comportamental.v"
`include "semaforo.v"
`include "lib.v"
`include "componentes_new.v"

module tb_semaforo;

    reg clk, res, CAR, TIMEOUT;
    wire VERDE_s, AMARELO_s, VERMELHO_s;
    wire VERDE_c, AMARELO_c, VERMELHO_c;

    // Instancia do semáforo arquitetural
    semaforo semaforo(.clk(clk), .res(res), .CAR(CAR), .TIMEOUT(TIMEOUT),
                  .VERDE(VERDE_s), .AMARELO(AMARELO_s), .VERMELHO(VERMELHO_s));

    // Instancia do modelo comportamental
    modelo_comportamental modelo_comportamental(.clk(clk), .res(res), .CAR(CAR), .TIMEOUT(TIMEOUT),
                               .VERDE(VERDE_c), .AMARELO(AMARELO_c), .VERMELHO(VERMELHO_c));

    // Clock 10ps
    initial clk = 0;
    always #5 clk = ~clk;

    // Sequência de estímulos
    initial begin
        res = 0; CAR = 0; TIMEOUT = 0;
        #12 res = 1;

        // Verde -> Amarelo
        #20 CAR = 1;
        #10 CAR = 0;
        #20;

        // Amarelo -> Vermelho
        #20;

        // Vermelho -> Verde
        #20 TIMEOUT = 1;
        #20 TIMEOUT = 0;
        #20;

        // Novo ciclo
        #20 CAR = 1;
        #20 CAR = 0;
        #20 TIMEOUT = 1;
        #20 TIMEOUT = 0;

        #50 $finish;
    end

    // Monitor
    initial begin
        $display("Time | CAR TIMEOUT | VERDE_s VERDE_c | AMARELO_s AMARELO_c | VERMELHO_s VERMELHO_c");
        $monitor("%4t | %b %b | %b %b | %b %b | %b %b",
                 $time, CAR, TIMEOUT,
                 VERDE_s, VERDE_c,
                 AMARELO_s, AMARELO_c,
                 VERMELHO_s, VERMELHO_c);
    end

    // Geração de ondas
    initial begin
        $dumpfile("tb_semaforo.vcd");
        $dumpvars(0, tb_semaforo);
    end
endmodule

APS3-Q5/tb_semaforo.vcd
$date
	Mon Nov 24 11:26:27 2025
$end
$version
	Icarus Verilog
$end
$timescale
	1ps
$end
$scope module tb_semaforo $end
$var wire 1 ! VERMELHO_s $end
$var wire 1 " VERMELHO_c $end
$var wire 1 # VERDE_s $end
$var wire 1 $ VERDE_c $end
$var wire 1 % AMARELO_s $end
$var wire 1 & AMARELO_c $end
$var reg 1 ' CAR $end
$var reg 1 ( TIMEOUT $end
$var reg 1 ) clk $end
$var reg 1 * res $end
$scope module modelo_comportamental $end
$var wire 1 ' CAR $end
$var wire 1 ( TIMEOUT $end
$var wire 1 ) clk $end
$var wire 1 * res $end
$var parameter 2 + S_AMARELO $end
$var parameter 2 , S_VERDE $end
$var parameter 2 - S_VERMELHO $end
$var reg 1 & AMARELO $end
$var reg 1 $ VERDE $end
$var reg 1 " VERMELHO $end
$var reg 2 . next_state [1:0] $end
$var reg 2 / state [1:0] $end
$upscope $end
$scope module semaforo $end
$var wire 1 % AMARELO $end
$var wire 1 ' CAR $end
$var wire 1 0 D0 $end
$var wire 1 1 D1 $end
$var wire 1 2 D1_term1 $end
$var wire 1 ( TIMEOUT $end
$var wire 1 # VERDE $end
$var wire 1 ! VERMELHO $end
$var wire 1 ) clk $end
$var wire 1 * res $end
$var wire 1 3 notTIMEOUT $end
$var wire 1 4 notQ1 $end
$var wire 1 5 notQ0 $end
$var wire 1 6 is_vermelho $end
$var wire 1 7 is_verde $end
$var wire 1 8 is_amarelo $end
$var wire 1 9 Q1n $end
$var wire 1 : Q1 $end
$var wire 1 ; Q0n $end
$var wire 1 < Q0 $end
$var wire 1 = D1_term2 $end
$var wire 1 > D1_expr $end
$var wire 1 ? D0_expr $end
$scope module and_D0 $end
$var wire 1 ' B $end
$var wire 1 ? F $end
$var wire 1 @ Fn $end
$var wire 1 7 A $end
$upscope $end
$scope module and_D1_term2 $end
$var wire 1 = F $end
$var wire 1 A Fn $end
$var wire 1 3 B $end
$var wire 1 6 A $end
$upscope $end
$scope module and_amarelo_state $end
$var wire 1 8 F $end
$var wire 1 B Fn $end
$var wire 1 < B $end
$var wire 1 4 A $end
$upscope $end
$scope module and_verde_state $end
$var wire 1 7 F $end
$var wire 1 C Fn $end
$var wire 1 5 B $end
$var wire 1 4 A $end
$upscope $end
$scope module and_vermelho_state $end
$var wire 1 6 F $end
$var wire 1 D Fn $end
$var wire 1 5 B $end
$var wire 1 : A $end
$upscope $end
$scope module ff0 $end
$var wire 1 ) Clock $end
$var wire 1 0 D $end
$var wire 1 E Preset $end
$var wire 1 * Reset $end
$var reg 1 < Q $end
$var reg 1 ; Qn $end
$upscope $end
$scope module ff1 $end
$var wire 1 ) Clock $end
$var wire 1 1 D $end
$var wire 1 F Preset $end
$var wire 1 * Reset $end
$var reg 1 : Q $end
$var reg 1 9 Qn $end
$upscope $end
$scope module inv0 $end
$var wire 1 < A $end
$var wire 1 5 F $end
$upscope $end
$scope module inv1 $end
$var wire 1 : A $end
$var wire 1 4 F $end
$upscope $end
$scope module invTIMEOUT $end
$var wire 1 ( A $end
$var wire 1 3 F $end
$upscope $end
$scope module or_D1 $end
$var wire 1 2 A $end
$var wire 1 = B $end
$var wire 1 > F $end
$var wire 1 G f1 $end
$var wire 1 H f2 $end
$upscope $end
$upscope $end
$upscope $end
$enddefinitions $end
$comment Show the parameter values. $end
$dumpall
b10 -
b0 ,
b1 +
$end
#0
$dumpvars
1H
1G
1F
1E
1D
0C
1B
1A
1@
0?
0>
0=
0<
1;
0:
19
08
17
06
15
14
13
02
01
00
b0 /
b0 .
0*
0)
0(
0'
0&
0%
1$
1#
0"
0!
$end
#5
1)
#10
0)
#12
1*
#15
1)
#20
0)
#25
1)
#30
0)
#32
10
1?
b1 .
0@
1'
#35
00
0?
1@
11
1>
0#
07
0G
1C
1%
12
18
b10 .
05
0B
b1 /
1&
0$
0;
1<
1)
#40
0)
#42
0'
#45
0H
1=
0A
11
1>
1!
16
1G
0D
0%
02
08
15
1B
04
1"
0&
b10 /
1;
0<
09
1:
1)
#50
0)
#55
1)
#60
0)
#65
1)
#70
0)
#75
1)
#80
0)
#85
1)
#90
0)
#95
1)
#100
0)
#102
01
0>
1H
0=
1A
b0 .
03
1(
#105
1#
17
0C
0!
06
14
1D
0"
1$
b0 /
19
0:
1)
#110
0)
#115
1)
#120
0)
#122
13
0(
#125
1)
#130
0)
#135
1)
#140
0)
#145
1)
#150
0)
#155
1)
#160
0)
#162
10
1?
b1 .
0@
1'
#165
00
0?
1@
11
1>
0#
07
0G
1C
1%
12
18
b10 .
05
0B
1&
0$
b1 /
0;
1<
1)
#170
0)
#175
0H
1=
0A
11
1>
1!
16
1G
0D
0%
02
08
15
1B
04
b10 /
1"
0&
1;
0<
09
1:
1)
#180
0)
#182
0'
#185
1)
#190
0)
#195
1)
#200
0)
#202
01
0>
1H
0=
1A
b0 .
03
1(
#205
1#
17
0C
0!
06
14
1D
0"
1$
b0 /
19
0:
1)
#210
0)
#215
1)
#220
0)
#222
13
0(
